iomux.py
iomux-0.2.0.dist-info/METADATA
iomux-0.2.0.dist-info/WHEEL
iomux-0.2.0.dist-info/RECORD
