Metadata-Version: 2.1
Name: iomux
Version: 0.2.0
Summary: IO buffer multiplexer
Keywords: io multiplexer mux bytesio stringio process capture
Home-page: https://github.com/FFY00/python-iomux
Author: Filipe Laíns <lains@riseup.net>
Author-Email: Filipe Laíns <lains@riseup.net>
Classifier: Development Status :: 4 - Beta
Classifier: Programming Language :: Python
Project-URL: Homepage, https://github.com/FFY00/python-iomux
Project-URL: Repository, https://github.com/FFY00/python-iomux
Requires-Python: >=3.7
Provides-Extra: test
Provides-Extra: docs
Requires-Dist: pytest; extra == "test"
Requires-Dist: pytest-cov; extra == "test"
Requires-Dist: furo>=2021.04.11b34; extra == "docs"
Requires-Dist: sphinx~=3.0; extra == "docs"
